dikshantprogress/__init__.py
dikshantprogress/core.py
dikshantprogress/utils.py
dikshantprogress-1.0.1.dist-info/licenses/LICENSE.txt
dikshantprogress-1.0.1.dist-info/METADATA
dikshantprogress-1.0.1.dist-info/WHEEL
dikshantprogress-1.0.1.dist-info/top_level.txt
dikshantprogress-1.0.1.dist-info/RECORD
