Metadata-Version: 2.4
Name: dikshantprogress
Version: 1.0.1
Summary: Customizable progress bars with time and event triggers
Author-email: Dikshant Ghimire <dikkughimire@gmail.com>
Project-URL: Homepage, https://github.com/dikshantgh/dikshantprogress
Classifier: Programming Language :: Python :: 3
Classifier: License :: OSI Approved :: MIT License
Classifier: Operating System :: OS Independent
Requires-Python: >=3.7
License-File: LICENSE.txt
Dynamic: license-file
